aracnid_logger/__init__.py
aracnid_logger/i_logger.py
aracnid_logger/slack_logger.py
aracnid_logger-1.0.2.dist-info/LICENSE
aracnid_logger-1.0.2.dist-info/WHEEL
aracnid_logger-1.0.2.dist-info/METADATA
aracnid_logger-1.0.2.dist-info/RECORD
