Metadata-Version: 2.1
Name: aracnid-logger
Version: 1.0.2
Summary: Customization of the Python Logging System
Home-page: https://github.com/aracnid/aracnid-logger
License: MIT
Keywords: python,logger
Author: Jason Romano
Author-email: aracnid@gmail.com
Requires-Python: >=3.10,<4.0
Classifier: License :: OSI Approved :: MIT License
Classifier: Programming Language :: Python :: 3
Classifier: Programming Language :: Python :: 3.10
Classifier: Programming Language :: Python :: 3.11
Requires-Dist: slack-bolt (>=1.14,<1.15)
Project-URL: Repository, https://github.com/aracnid/aracnid-logger
